{
  "name": "Mir Sazzat Hossain",
  "photo": "/images/user.webp",
  "designation": "Research Assistant",
  "company": {
    "name": "Independent University, Bangladesh",
    "url": "https://iub.ac.bd/",
    "department": {
      "name": "Center for Computational & Data Sciences",
      "url": "https://ccds.ai/"
    }
  },
  "researchInterests": [
    "Multimodal Learning",
    "Domain Adaptation",
    "CUAs",
    "Vision-Language Models",
    "Federated Learning"
  ],
  "description": "A highly motivated and aspiring researcher with a strong background in deep learning, with recent work centered on multimodal learning. Over the past few years, I have actively contributed to the field, publishing research articles in top-tier venues such as ACL and WACV. My primary research interests lie in vision-language models. I have also worked on domain adaptation and federated learning, and continue to explore these areas with strong interest.\n\nCurrently, I am working as a Research Assistant at the Center for Computational & Data Sciences (CCDS) at Independent University, Bangladesh. My recent work explores multimodal alignment, efficient adaptation, and generative approaches, including diffusion models and constrained generation. I am actively seeking Ph.D. opportunities in Computer Science, with an emphasis on vision-language models, domain adaptation, and generative models.",
  "academicLinks": [
    {
      "name": "google-scholar",
      "url": "https://scholar.google.com/citations?user=HriPgEQAAAAJ"
    },
    {
      "name": "semantic-scholar",
      "url": "https://www.semanticscholar.org/author/Mir-Sazzat-Hossain/2220031205"
    },
    {
      "name": "dblp",
      "url": "https://dblp.org/pid/349/0737.html"
    },
    {
      "name": "acl",
      "url": "https://aclanthology.org/people/mir-sazzat-hossain/"
    },
    {
      "name": "openreview",
      "url": "https://openreview.net/profile?id=~Mir_Sazzat_Hossain1"
    },
    {
      "name": "github",
      "url": "https://github.com/mirsazzathossain"
    }
  ],
  "socialLinks": [
    {
      "name": "linkedin",
      "url": "https://www.linkedin.com/in/mirsazzathossain/",
      "username": "mirsazzathossain"
    },
    {
      "name": "discord",
      "url": "https://discord.gg/M7Jjv9hr",
      "username": "mirsazzathossain"
    }
  ],
  "resume": "files/mirsazzathossain-cv.pdf",
  "availability": "Applying for Fall 2026 PhD",
  "location": {
    "name": "Dhaka, Bangladesh",
    "url": "https://www.google.com/maps/place/Dhaka/@23.7810672,90.2548772,11z/"
  },
  "email": "mirsazzathossain@gmail.com"
}
